{
  "layout": "post",
  "id": "a1mP74b",
  "url": "/2025/01/06/a1mP74b.html",
  "post_url": "/2025/01/06/a1mP74b.html",
  "title": "Laptop powered Battle station",
  "description": "",
  "type": "Photo",
  "nsfw": 0,
  "upVoteCount": 1,
  "downVoteCount": 0,
  "creationTs": 1736124141,
  "promoted": 0,
  "badges": [],
  "images": {
    "image700": {
      "width": 700,
      "height": 525,
      "url": "/assets/media/a1mP74b_image700.jpg"
    },
    "image460": {
      "width": 460,
      "height": 345,
      "url": "/assets/media/a1mP74b_image460.jpg"
    }
  },
  "commentsCount": 0,
  "tags": [
    {
      "key": "pcmr",
      "url": "/tag/pcmr"
    },
    {
      "key": "battle stations",
      "url": "/tag/battle-stations"
    }
  ],
  "interests": [
    "games"
  ]
}