{
  "layout": "post",
  "id": "a1mPRdb",
  "url": "/2025/01/03/a1mPRdb.html",
  "post_url": "/2025/01/03/a1mPRdb.html",
  "title": "Of these large lads (esp. bottom left)",
  "description": "",
  "type": "Photo",
  "nsfw": 0,
  "upVoteCount": 0,
  "downVoteCount": 0,
  "creationTs": 1735870402,
  "promoted": 0,
  "badges": [],
  "images": {
    "image700": {
      "width": 700,
      "height": 834,
      "url": "/assets/media/a1mPRdb_image700.jpg"
    },
    "image460": {
      "width": 460,
      "height": 548,
      "url": "/assets/media/a1mPRdb_image460.jpg"
    }
  },
  "commentsCount": 0,
  "tags": [
    {
      "key": "Absolute Units",
      "url": "/tag/absolute-units"
    }
  ],
  "interests": [
    "woah"
  ]
}