{
  "layout": "post",
  "id": "a2vKMQd",
  "url": "/2025/01/06/a2vKMQd.html",
  "post_url": "/2025/01/06/a2vKMQd.html",
  "title": "Bay Windows workstation. Windows/Mac/Linux.",
  "description": "",
  "type": "Photo",
  "nsfw": 0,
  "upVoteCount": 1,
  "downVoteCount": 0,
  "creationTs": 1736124140,
  "promoted": 0,
  "badges": [],
  "images": {
    "image700": {
      "width": 700,
      "height": 525,
      "url": "/assets/media/a2vKMQd_image700.jpg"
    },
    "image460": {
      "width": 460,
      "height": 345,
      "url": "/assets/media/a2vKMQd_image460.jpg"
    }
  },
  "commentsCount": 0,
  "tags": [
    {
      "key": "pcmr",
      "url": "/tag/pcmr"
    },
    {
      "key": "battle stations",
      "url": "/tag/battle-stations"
    }
  ],
  "interests": [
    "games"
  ]
}