{
  "layout": "post",
  "id": "a9yqEOK",
  "url": "/2025/01/04/a9yqEOK.html",
  "post_url": "/2025/01/04/a9yqEOK.html",
  "title": "Pork or chicken or beef or seafood...no ALL veggies junktard...",
  "description": "",
  "type": "Photo",
  "nsfw": 0,
  "upVoteCount": 12,
  "downVoteCount": 10,
  "creationTs": 1735967547,
  "promoted": 0,
  "badges": [],
  "images": {
    "image700": {
      "width": 550,
      "height": 455,
      "url": "/assets/media/a9yqEOK_image700.jpg"
    },
    "image460": {
      "width": 460,
      "height": 380,
      "url": "/assets/media/a9yqEOK_image460.jpg"
    }
  },
  "commentsCount": 1,
  "tags": [
    {
      "key": "you legend who make sense",
      "url": "/tag/you-legend-who-make-sense"
    },
    {
      "key": "nightmare fix",
      "url": "/tag/nightmare-fix"
    },
    {
      "key": "all you can eat",
      "url": "/tag/all-you-can-eat"
    },
    {
      "key": "let me eat it all",
      "url": "/tag/let-me-eat-it-all"
    }
  ],
  "interests": [
    "random"
  ]
}