{
  "layout": "post",
  "id": "a9yq626",
  "url": "/2025/01/06/a9yq626.html",
  "post_url": "/2025/01/06/a9yq626.html",
  "title": "Guess the Character",
  "description": "",
  "type": "Photo",
  "nsfw": 0,
  "upVoteCount": 3,
  "downVoteCount": 14,
  "creationTs": 1736151255,
  "promoted": 0,
  "badges": [],
  "images": {
    "image700": {
      "width": 480,
      "height": 640,
      "url": "/assets/media/a9yq626_image700.jpg"
    },
    "image460": {
      "width": 460,
      "height": 613,
      "url": "/assets/media/a9yq626_image460.jpg"
    }
  },
  "commentsCount": 8,
  "tags": [
    {
      "key": "Guess",
      "url": "/tag/guess"
    },
    {
      "key": "the",
      "url": "/tag/the"
    },
    {
      "key": "character",
      "url": "/tag/character"
    }
  ],
  "interests": [
    "random"
  ]
}