{
  "layout": "post",
  "id": "aAy0GGg",
  "url": "/2025/01/04/aAy0GGg.html",
  "post_url": "/2025/01/04/aAy0GGg.html",
  "title": "Life is peaceful there.",
  "description": "",
  "type": "Photo",
  "nsfw": 0,
  "upVoteCount": 51,
  "downVoteCount": 25,
  "creationTs": 1735998189,
  "promoted": 0,
  "badges": [],
  "images": {
    "image700": {
      "width": 599,
      "height": 389,
      "url": "/assets/media/aAy0GGg_image700.jpg"
    },
    "image460": {
      "width": 460,
      "height": 298,
      "url": "/assets/media/aAy0GGg_image460.jpg"
    }
  },
  "commentsCount": 8,
  "tags": [
    {
      "key": "doctor",
      "url": "/tag/doctor"
    },
    {
      "key": "engineer",
      "url": "/tag/engineer"
    },
    {
      "key": "dark humor",
      "url": "/tag/dark-humor"
    }
  ],
  "interests": [
    "memes"
  ]
}