{
  "layout": "post",
  "id": "abAvrV8",
  "url": "/2025/01/03/abAvrV8.html",
  "post_url": "/2025/01/03/abAvrV8.html",
  "title": "When big machines and men meet little boys with trucks",
  "description": "",
  "type": "Animated",
  "nsfw": 0,
  "upVoteCount": 1603,
  "downVoteCount": 135,
  "creationTs": 1735879396,
  "promoted": 0,
  "badges": [],
  "images": {
    "image700": {
      "width": 360,
      "height": 640,
      "url": "/assets/media/abAvrV8_image700.jpg"
    },
    "image460": {
      "width": 360,
      "height": 640,
      "url": "/assets/media/abAvrV8_image460.jpg"
    },
    "image460sv": {
      "width": 360,
      "height": 640,
      "url": "/assets/media/abAvrV8_video.mp4",
      "hasAudio": 1,
      "duration": 17
    }
  },
  "commentsCount": 49,
  "tags": [
    {
      "key": "wholesome",
      "url": "/tag/wholesome"
    }
  ],
  "interests": [
    "wholesome"
  ]
}