{
  "layout": "post",
  "id": "agmog3v",
  "url": "/2025/01/04/agmog3v.html",
  "post_url": "/2025/01/04/agmog3v.html",
  "title": "The Moon landing",
  "description": "",
  "type": "Animated",
  "nsfw": 0,
  "upVoteCount": 77,
  "downVoteCount": 43,
  "creationTs": 1735985240,
  "promoted": 0,
  "badges": [],
  "images": {
    "image700": {
      "width": 460,
      "height": 817,
      "url": "/assets/media/agmog3v_image700.jpg"
    },
    "image460": {
      "width": 460,
      "height": 817,
      "url": "/assets/media/agmog3v_image460.jpg"
    },
    "image460sv": {
      "width": 460,
      "height": 816,
      "url": "/assets/media/agmog3v_video.mp4",
      "hasAudio": 1,
      "duration": 54
    }
  },
  "commentsCount": 29,
  "tags": [
    {
      "key": "christopher nolan",
      "url": "/tag/christopher-nolan"
    },
    {
      "key": "brian cox",
      "url": "/tag/brian-cox"
    },
    {
      "key": "moon",
      "url": "/tag/moon"
    },
    {
      "key": "moon landing",
      "url": "/tag/moon-landing"
    }
  ],
  "interests": [
    "science"
  ]
}