{
  "layout": "post",
  "id": "aGyEdAX",
  "url": "/2025/01/03/aGyEdAX.html",
  "post_url": "/2025/01/03/aGyEdAX.html",
  "title": "The blue whale, reaching a confirmed maximum length of 29.9 meters (98 ft) and weighing up to 199 tons, is the largest animal known to have ever existed.",
  "description": "",
  "type": "Animated",
  "nsfw": 0,
  "upVoteCount": 0,
  "downVoteCount": 0,
  "creationTs": 1735926849,
  "promoted": 0,
  "badges": [],
  "images": {
    "image700": {
      "width": 460,
      "height": 818,
      "url": "/assets/media/aGyEdAX_image700.jpg"
    },
    "image460": {
      "width": 460,
      "height": 818,
      "url": "/assets/media/aGyEdAX_image460.jpg"
    },
    "image460sv": {
      "width": 460,
      "height": 818,
      "url": "/assets/media/aGyEdAX_video.mp4",
      "hasAudio": 1,
      "duration": 13
    }
  },
  "commentsCount": 0,
  "tags": [
    {
      "key": "awesome",
      "url": "/tag/awesome"
    },
    {
      "key": "amazed",
      "url": "/tag/amazed"
    }
  ],
  "interests": [
    "woah"
  ]
}