{
  "layout": "post",
  "id": "amoAGQX",
  "url": "/2025/01/07/amoAGQX.html",
  "post_url": "/2025/01/07/amoAGQX.html",
  "title": "S.O.S",
  "description": "",
  "type": "Photo",
  "nsfw": 0,
  "upVoteCount": 0,
  "downVoteCount": 0,
  "creationTs": 1736189711,
  "promoted": 0,
  "badges": [],
  "images": {
    "image700": {
      "width": 700,
      "height": 1244,
      "url": "/assets/media/amoAGQX_image700.jpg"
    },
    "image460": {
      "width": 460,
      "height": 817,
      "url": "/assets/media/amoAGQX_image460.jpg"
    }
  },
  "commentsCount": 0,
  "tags": [
    {
      "key": "shitty food porn",
      "url": "/tag/shitty-food-porn"
    }
  ],
  "interests": [
    "wtf"
  ]
}