{
  "layout": "post",
  "id": "amoA1Q4",
  "url": "/2025/01/06/amoA1Q4.html",
  "post_url": "/2025/01/06/amoA1Q4.html",
  "title": "A leader from Africa is what she's looking for, stay away white people",
  "description": "",
  "type": "Photo",
  "nsfw": 0,
  "upVoteCount": 9,
  "downVoteCount": 43,
  "creationTs": 1736161302,
  "promoted": 0,
  "badges": [],
  "images": {
    "image700": {
      "width": 700,
      "height": 1281,
      "url": "/assets/media/amoA1Q4_image700.jpg"
    },
    "image460": {
      "width": 460,
      "height": 842,
      "url": "/assets/media/amoA1Q4_image460.jpg"
    }
  },
  "commentsCount": 29,
  "tags": [
    {
      "key": "wholesome memes",
      "url": "/tag/wholesome-memes"
    }
  ],
  "interests": [
    "memes"
  ]
}