{
  "layout": "post",
  "id": "aMVE49P",
  "url": "/2025/01/04/aMVE49P.html",
  "post_url": "/2025/01/04/aMVE49P.html",
  "title": "Collision with power lines at over 200 kilometers per hour. Pilot survived.",
  "description": "",
  "type": "Animated",
  "nsfw": 0,
  "upVoteCount": 224,
  "downVoteCount": 17,
  "creationTs": 1735990951,
  "promoted": 0,
  "badges": [],
  "images": {
    "image700": {
      "width": 460,
      "height": 398,
      "url": "/assets/media/aMVE49P_image700.jpg"
    },
    "image460": {
      "width": 460,
      "height": 398,
      "url": "/assets/media/aMVE49P_image460.jpg"
    },
    "image460sv": {
      "width": 460,
      "height": 398,
      "url": "/assets/media/aMVE49P_video.mp4",
      "hasAudio": 1,
      "duration": 36
    }
  },
  "commentsCount": 38,
  "tags": [
    {
      "key": "random",
      "url": "/tag/random"
    },
    {
      "key": "abrupt chaos",
      "url": "/tag/abrupt-chaos"
    }
  ],
  "interests": [
    "wtf",
    "random"
  ]
}