{
  "layout": "post",
  "id": "an7zz9B",
  "url": "/2025/01/05/an7zz9B.html",
  "post_url": "/2025/01/05/an7zz9B.html",
  "title": "Orphan adoption 🍊",
  "description": "",
  "type": "Animated",
  "nsfw": 0,
  "upVoteCount": 97,
  "downVoteCount": 14,
  "creationTs": 1736026351,
  "promoted": 0,
  "badges": [],
  "images": {
    "image700": {
      "width": 360,
      "height": 640,
      "url": "/assets/media/an7zz9B_image700.jpg"
    },
    "image460": {
      "width": 360,
      "height": 640,
      "url": "/assets/media/an7zz9B_image460.jpg"
    },
    "image460sv": {
      "width": 360,
      "height": 640,
      "url": "/assets/media/an7zz9B_video.mp4",
      "hasAudio": 1,
      "duration": 29
    }
  },
  "commentsCount": 3,
  "tags": [
    {
      "key": "funny",
      "url": "/tag/funny"
    },
    {
      "key": "animal",
      "url": "/tag/animal"
    }
  ],
  "interests": [
    "animals"
  ]
}