{
  "layout": "post",
  "id": "aoyKOwg",
  "url": "/2025/01/02/aoyKOwg.html",
  "post_url": "/2025/01/02/aoyKOwg.html",
  "title": "Time to give DEI a new meaning.",
  "description": "",
  "type": "Photo",
  "nsfw": 0,
  "upVoteCount": 15,
  "downVoteCount": 63,
  "creationTs": 1735780128,
  "promoted": 0,
  "badges": [],
  "images": {
    "image700": {
      "width": 700,
      "height": 492,
      "url": "/assets/media/aoyKOwg_image700.jpg"
    },
    "image460": {
      "width": 460,
      "height": 323,
      "url": "/assets/media/aoyKOwg_image460.jpg"
    }
  },
  "commentsCount": 9,
  "tags": [
    {
      "key": "dei",
      "url": "/tag/dei"
    },
    {
      "key": "get woke go broke",
      "url": "/tag/get-woke-go-broke"
    }
  ],
  "interests": [
    "news",
    "science"
  ]
}