{
  "layout": "post",
  "id": "aRBEEXA",
  "url": "/2025/01/05/aRBEEXA.html",
  "post_url": "/2025/01/05/aRBEEXA.html",
  "title": "400 days without snusnu",
  "description": "",
  "type": "Photo",
  "nsfw": 0,
  "upVoteCount": 57,
  "downVoteCount": 30,
  "creationTs": 1736027857,
  "promoted": 0,
  "badges": [],
  "images": {
    "image700": {
      "width": 460,
      "height": 690,
      "url": "/assets/media/aRBEEXA_image700.jpg"
    },
    "image460": {
      "width": 460,
      "height": 690,
      "url": "/assets/media/aRBEEXA_image460.jpg"
    }
  },
  "commentsCount": 7,
  "tags": [
    {
      "key": "simpsons",
      "url": "/tag/simpsons"
    },
    {
      "key": "dating",
      "url": "/tag/dating"
    },
    {
      "key": "tinder",
      "url": "/tag/tinder"
    }
  ],
  "interests": [
    "humor",
    "relationship"
  ]
}