{
  "layout": "post",
  "id": "aRBEjXQ",
  "url": "/2025/01/02/aRBEjXQ.html",
  "post_url": "/2025/01/02/aRBEjXQ.html",
  "title": "Question of the day!",
  "description": "",
  "type": "Photo",
  "nsfw": 0,
  "upVoteCount": 15,
  "downVoteCount": 11,
  "creationTs": 1735762414,
  "promoted": 0,
  "badges": [],
  "images": {
    "image700": {
      "width": 700,
      "height": 875,
      "url": "/assets/media/aRBEjXQ_image700.jpg"
    },
    "image460": {
      "width": 460,
      "height": 575,
      "url": "/assets/media/aRBEjXQ_image460.jpg"
    }
  },
  "commentsCount": 8,
  "tags": [
    {
      "key": "warhammer",
      "url": "/tag/warhammer"
    }
  ],
  "interests": [
    "games"
  ]
}