{
  "layout": "post",
  "id": "arymmm5",
  "url": "/2025/01/05/arymmm5.html",
  "post_url": "/2025/01/05/arymmm5.html",
  "title": "This guy has an amazing story. He escaped and now he's speaking truth in front of crowds",
  "description": "",
  "type": "Animated",
  "nsfw": 0,
  "upVoteCount": 19,
  "downVoteCount": 72,
  "creationTs": 1736030187,
  "promoted": 0,
  "badges": [],
  "images": {
    "image700": {
      "width": 460,
      "height": 817,
      "url": "/assets/media/arymmm5_image700.jpg"
    },
    "image460": {
      "width": 460,
      "height": 817,
      "url": "/assets/media/arymmm5_image460.jpg"
    },
    "image460sv": {
      "width": 460,
      "height": 816,
      "url": "/assets/media/arymmm5_video.mp4",
      "hasAudio": 1,
      "duration": 60
    }
  },
  "commentsCount": 19,
  "tags": [
    {
      "key": "9gag news",
      "url": "/tag/9gag-news"
    }
  ],
  "interests": [
    "news"
  ]
}