{
  "layout": "post",
  "id": "arym427",
  "url": "/2024/12/30/arym427.html",
  "post_url": "/2024/12/30/arym427.html",
  "title": "This is how the squirrels fell asleep with their spouses.",
  "description": "",
  "type": "Animated",
  "nsfw": 0,
  "upVoteCount": 4146,
  "downVoteCount": 46,
  "creationTs": 1735563152,
  "promoted": 0,
  "badges": [],
  "images": {
    "image700": {
      "width": 360,
      "height": 624,
      "url": "/assets/media/arym427_image700.jpg"
    },
    "image460": {
      "width": 360,
      "height": 624,
      "url": "/assets/media/arym427_image460.jpg"
    },
    "image460sv": {
      "width": 360,
      "height": 624,
      "url": "/assets/media/arym427_video.mp4",
      "hasAudio": 1,
      "duration": 19
    }
  },
  "commentsCount": 63,
  "tags": [
    {
      "key": "animals",
      "url": "/tag/animals"
    },
    {
      "key": "aww",
      "url": "/tag/aww"
    }
  ],
  "interests": [
    "animals"
  ]
}