{
  "layout": "post",
  "id": "aW4G1Kn",
  "url": "/2025/01/02/aW4G1Kn.html",
  "post_url": "/2025/01/02/aW4G1Kn.html",
  "title": "Your cyber truck when you say that you don't like Indians.",
  "description": "",
  "type": "Animated",
  "nsfw": 0,
  "upVoteCount": 14,
  "downVoteCount": 29,
  "creationTs": 1735828880,
  "promoted": 0,
  "badges": [],
  "images": {
    "image700": {
      "width": 460,
      "height": 804,
      "url": "/assets/media/aW4G1Kn_image700.jpg"
    },
    "image460": {
      "width": 460,
      "height": 804,
      "url": "/assets/media/aW4G1Kn_image460.jpg"
    },
    "image460sv": {
      "width": 460,
      "height": 804,
      "url": "/assets/media/aW4G1Kn_video.mp4",
      "hasAudio": 1,
      "duration": 8
    }
  },
  "commentsCount": 30,
  "tags": [
    {
      "key": "politics",
      "url": "/tag/politics"
    }
  ],
  "interests": [
    "humor",
    "news"
  ]
}