{
  "layout": "post",
  "id": "ayN2qOY",
  "url": "/2025/01/06/ayN2qOY.html",
  "post_url": "/2025/01/06/ayN2qOY.html",
  "title": "Producers for the X-Files originally wanted Bruce Campbell for Mulder and Pamela Anderson as Scully. I can see Bruce, but the chemistry between David and Gillian was gold.",
  "description": "",
  "type": "Photo",
  "nsfw": 0,
  "upVoteCount": 15,
  "downVoteCount": 15,
  "creationTs": 1736123054,
  "promoted": 0,
  "badges": [],
  "images": {
    "image700": {
      "width": 700,
      "height": 895,
      "url": "/assets/media/ayN2qOY_image700.jpg"
    },
    "image460": {
      "width": 460,
      "height": 588,
      "url": "/assets/media/ayN2qOY_image460.jpg"
    }
  },
  "commentsCount": 12,
  "tags": [
    {
      "key": "xfiles",
      "url": "/tag/xfiles"
    },
    {
      "key": "bruce campbell",
      "url": "/tag/bruce-campbell"
    },
    {
      "key": "pamela anderson",
      "url": "/tag/pamela-anderson"
    }
  ],
  "interests": [
    "movies"
  ]
}