{
  "layout": "post",
  "id": "aZZDg30",
  "url": "/2025/01/02/aZZDg30.html",
  "post_url": "/2025/01/02/aZZDg30.html",
  "title": "New Years Message To Not an yahoo",
  "description": "",
  "type": "Animated",
  "nsfw": 0,
  "upVoteCount": 4,
  "downVoteCount": 28,
  "creationTs": 1735759996,
  "promoted": 0,
  "badges": [],
  "images": {
    "image700": {
      "width": 460,
      "height": 258,
      "url": "/assets/media/aZZDg30_image700.jpg"
    },
    "image460": {
      "width": 460,
      "height": 258,
      "url": "/assets/media/aZZDg30_image460.jpg"
    },
    "image460sv": {
      "width": 460,
      "height": 258,
      "url": "/assets/media/aZZDg30_video.mp4",
      "hasAudio": 1,
      "duration": 550
    }
  },
  "commentsCount": 3,
  "tags": [
    {
      "key": "palestine",
      "url": "/tag/palestine"
    },
    {
      "key": "islam",
      "url": "/tag/islam"
    }
  ],
  "interests": [
    "news"
  ]
}