{
  "layout": "post",
  "id": "a0e45on",
  "url": "/2025/01/02/a0e45on.html",
  "post_url": "/2025/01/02/a0e45on.html",
  "title": "Tell your best Chuck Norris joke in the comments",
  "description": "",
  "type": "Photo",
  "nsfw": 0,
  "upVoteCount": 48,
  "downVoteCount": 27,
  "creationTs": 1735765763,
  "promoted": 0,
  "badges": [],
  "images": {
    "image700": {
      "width": 275,
      "height": 183,
      "url": "/assets/media/a0e45on_image700.jpg"
    },
    "image460": {
      "width": 275,
      "height": 183,
      "url": "/assets/media/a0e45on_image460.jpg"
    }
  },
  "commentsCount": 12,
  "tags": [
    {
      "key": "chuck norris",
      "url": "/tag/chuck-norris"
    },
    {
      "key": "chuck norris facts",
      "url": "/tag/chuck-norris-facts"
    }
  ],
  "interests": [
    "memes"
  ]
}