{
  "layout": "post",
  "id": "aAy03zL",
  "url": "/2025/01/03/aAy03zL.html",
  "post_url": "/2025/01/03/aAy03zL.html",
  "title": "Look how sweet are his eyes",
  "description": "",
  "type": "Photo",
  "nsfw": 0,
  "upVoteCount": 1,
  "downVoteCount": 0,
  "creationTs": 1735857211,
  "promoted": 0,
  "badges": [],
  "images": {
    "image700": {
      "width": 700,
      "height": 608,
      "url": "/assets/media/aAy03zL_image700.jpg"
    },
    "image460": {
      "width": 460,
      "height": 399,
      "url": "/assets/media/aAy03zL_image460.jpg"
    }
  },
  "commentsCount": 0,
  "tags": [
    {
      "key": "animals",
      "url": "/tag/animals"
    },
    {
      "key": "aww",
      "url": "/tag/aww"
    }
  ],
  "interests": [
    "animals"
  ]
}