{
  "layout": "post",
  "id": "adBP6dN",
  "url": "http://9gag.com/gag/adBP6dN",
  "post_url": "/2024/12/30/adBP6dN.html",
  "title": "She saved John Wick",
  "description": "",
  "type": "Photo",
  "nsfw": 0,
  "upVoteCount": 10530,
  "downVoteCount": 267,
  "creationTs": 1735522938,
  "promoted": 0,
  "badges": [
    {
      "type": "top-post",
      "date": "2024-12-30",
      "rank": 9
    }
  ],
  "images": {
    "image700": {
      "width": 700,
      "height": 875,
      "url": "/assets/media/adBP6dN_image700.jpg",
      "webpUrl": "https://img-9gag-fun.9cache.com/photo/adBP6dN_700bwp.webp"
    },
    "image460": {
      "width": 460,
      "height": 575,
      "url": "https://img-9gag-fun.9cache.com/photo/adBP6dN_460s.jpg",
      "webpUrl": "https://img-9gag-fun.9cache.com/photo/adBP6dN_460swp.webp"
    },
    "imageFbThumbnail": {
      "width": 220,
      "height": 220,
      "url": "https://img-9gag-fun.9cache.com/photo/adBP6dN_fbthumbnail.jpg"
    }
  },
  "creator": {
    "userId": "32303870",
    "accountId": "32885745",
    "username": "robertclent",
    "fullName": "robertclent",
    "emojiStatus": "",
    "about": "My Funny Collection",
    "avatarUrl": "https://accounts-cdn.9gag.com/media/avatar/32885745_100_1.jpg",
    "profileUrl": "https://9gag.com/u/robertclent",
    "isActivePro": false,
    "isActiveProPlus": false,
    "isVerifiedAccount": false,
    "creationTs": 1452277445,
    "activeTs": 1735633905,
    "preferences": {
      "hideProBadge": 0,
      "hideActiveTs": 0,
      "accentColor": "",
      "backgroundColor": ""
    }
  },
  "commentsCount": 370,
  "tags": [
    {
      "key": "Funny",
      "url": "/tag/funny"
    },
    {
      "key": "Wow",
      "url": "/tag/wow"
    }
  ],
  "interests": [
    "humor",
    "woah"
  ]
}