{
  "layout": "post",
  "id": "ae9Q5XB",
  "url": "/2025/01/03/ae9Q5XB.html",
  "post_url": "/2025/01/03/ae9Q5XB.html",
  "title": "Everything is going fine in the Imperium of Man!",
  "description": "",
  "type": "Photo",
  "nsfw": 0,
  "upVoteCount": 3350,
  "downVoteCount": 93,
  "creationTs": 1735909054,
  "promoted": 0,
  "badges": [],
  "images": {
    "image700": {
      "width": 700,
      "height": 900,
      "url": "/assets/media/ae9Q5XB_image700.jpg"
    },
    "image460": {
      "width": 460,
      "height": 591,
      "url": "/assets/media/ae9Q5XB_image460.jpg"
    }
  },
  "commentsCount": 71,
  "tags": [
    {
      "key": "gaming",
      "url": "/tag/gaming"
    },
    {
      "key": "warhammer",
      "url": "/tag/warhammer"
    },
    {
      "key": "Pain Harold",
      "url": "/tag/pain-harold"
    }
  ],
  "interests": [
    "games"
  ]
}