{
  "layout": "post",
  "id": "aLn1jXA",
  "url": "/2025/01/02/aLn1jXA.html",
  "post_url": "/2025/01/02/aLn1jXA.html",
  "title": "When you’ve not been trading well but you’re still optimistic!",
  "description": "",
  "type": "Photo",
  "nsfw": 0,
  "upVoteCount": 5,
  "downVoteCount": 1,
  "creationTs": 1735815744,
  "promoted": 0,
  "badges": [],
  "images": {
    "image700": {
      "width": 600,
      "height": 969,
      "url": "/assets/media/aLn1jXA_image700.jpg"
    },
    "image460": {
      "width": 460,
      "height": 742,
      "url": "/assets/media/aLn1jXA_image460.jpg"
    }
  },
  "commentsCount": 1,
  "tags": [
    {
      "key": "crypto",
      "url": "/tag/crypto"
    },
    {
      "key": "cryptocurrency",
      "url": "/tag/cryptocurrency"
    }
  ],
  "interests": [
    "crypto"
  ]
}