{
  "layout": "post",
  "id": "aMVEKO6",
  "url": "/2025/01/04/aMVEKO6.html",
  "post_url": "/2025/01/04/aMVEKO6.html",
  "title": "Smith & Wesson 80% off on Temu",
  "description": "",
  "type": "Animated",
  "nsfw": 0,
  "upVoteCount": 67,
  "downVoteCount": 46,
  "creationTs": 1735968044,
  "promoted": 0,
  "badges": [],
  "images": {
    "image700": {
      "width": 460,
      "height": 413,
      "url": "/assets/media/aMVEKO6_image700.jpg"
    },
    "image460": {
      "width": 460,
      "height": 413,
      "url": "/assets/media/aMVEKO6_image460.jpg"
    },
    "image460sv": {
      "width": 460,
      "height": 412,
      "url": "/assets/media/aMVEKO6_video.mp4",
      "hasAudio": 1,
      "duration": 5
    }
  },
  "commentsCount": 14,
  "tags": [
    {
      "key": "Gangsta",
      "url": "/tag/gangsta"
    },
    {
      "key": "Fail",
      "url": "/tag/fail"
    },
    {
      "key": "Funny",
      "url": "/tag/funny"
    }
  ],
  "interests": [
    "humor"
  ]
}