{
  "layout": "post",
  "id": "aMVEZnV",
  "url": "/2025/01/03/aMVEZnV.html",
  "post_url": "/2025/01/03/aMVEZnV.html",
  "title": "MITCHELL, Cockblock of the winter-mist, love-void.",
  "description": "",
  "type": "Photo",
  "nsfw": 0,
  "upVoteCount": 6,
  "downVoteCount": 1,
  "creationTs": 1735845799,
  "promoted": 0,
  "badges": [],
  "images": {
    "image700": {
      "width": 700,
      "height": 670,
      "url": "/assets/media/aMVEZnV_image700.jpg"
    },
    "image460": {
      "width": 460,
      "height": 440,
      "url": "/assets/media/aMVEZnV_image460.jpg"
    }
  },
  "commentsCount": 0,
  "tags": [
    {
      "key": "wtf",
      "url": "/tag/wtf"
    },
    {
      "key": "boss fight",
      "url": "/tag/boss-fight"
    }
  ],
  "interests": [
    "humor"
  ]
}