{
  "layout": "post",
  "id": "an7z96L",
  "url": "/2025/01/03/an7z96L.html",
  "post_url": "/2025/01/03/an7z96L.html",
  "title": "Deadly assasin",
  "description": "",
  "type": "Animated",
  "nsfw": 0,
  "upVoteCount": 0,
  "downVoteCount": 0,
  "creationTs": 1735859055,
  "promoted": 0,
  "badges": [],
  "images": {
    "image700": {
      "width": 460,
      "height": 743,
      "url": "/assets/media/an7z96L_image700.jpg"
    },
    "image460": {
      "width": 460,
      "height": 743,
      "url": "/assets/media/an7z96L_image460.jpg"
    },
    "image460sv": {
      "width": 460,
      "height": 742,
      "url": "/assets/media/an7z96L_video.mp4",
      "hasAudio": 1,
      "duration": 8
    }
  },
  "commentsCount": 0,
  "tags": [
    {
      "key": "sips tea",
      "url": "/tag/sips-tea"
    }
  ],
  "interests": [
    "random"
  ]
}