{
  "layout": "post",
  "id": "aoyKPEe",
  "url": "/2025/01/03/aoyKPEe.html",
  "post_url": "/2025/01/03/aoyKPEe.html",
  "title": "Head Of Godzilla to scale, Shinjuku, Tokyo.",
  "description": "",
  "type": "Photo",
  "nsfw": 0,
  "upVoteCount": 0,
  "downVoteCount": 0,
  "creationTs": 1735910595,
  "promoted": 0,
  "badges": [],
  "images": {
    "image700": {
      "width": 700,
      "height": 933,
      "url": "/assets/media/aoyKPEe_image700.jpg"
    },
    "image460": {
      "width": 460,
      "height": 613,
      "url": "/assets/media/aoyKPEe_image460.jpg"
    }
  },
  "commentsCount": 0,
  "tags": [
    {
      "key": "random pics",
      "url": "/tag/random-pics"
    }
  ],
  "interests": [
    "random"
  ]
}