{
  "layout": "post",
  "id": "aRBE7mM",
  "url": "/2025/01/03/aRBE7mM.html",
  "post_url": "/2025/01/03/aRBE7mM.html",
  "title": "Horse around",
  "description": "",
  "type": "Animated",
  "nsfw": 0,
  "upVoteCount": 185,
  "downVoteCount": 44,
  "creationTs": 1735917072,
  "promoted": 0,
  "badges": [],
  "images": {
    "image700": {
      "width": 460,
      "height": 817,
      "url": "/assets/media/aRBE7mM_image700.jpg"
    },
    "image460": {
      "width": 460,
      "height": 817,
      "url": "/assets/media/aRBE7mM_image460.jpg"
    },
    "image460sv": {
      "width": 460,
      "height": 816,
      "url": "/assets/media/aRBE7mM_video.mp4",
      "hasAudio": 1,
      "duration": 7
    }
  },
  "commentsCount": 15,
  "tags": [
    {
      "key": "weird",
      "url": "/tag/weird"
    },
    {
      "key": "unexpected",
      "url": "/tag/unexpected"
    },
    {
      "key": "random",
      "url": "/tag/random"
    },
    {
      "key": "wtf",
      "url": "/tag/wtf"
    }
  ],
  "interests": [
    "humor",
    "sports",
    "wtf",
    "random"
  ]
}