{
  "layout": "post",
  "id": "avyQ12q",
  "url": "/2025/01/06/avyQ12q.html",
  "post_url": "/2025/01/06/avyQ12q.html",
  "title": "Rick & Morty mash up",
  "description": "",
  "type": "Photo",
  "nsfw": 0,
  "upVoteCount": 1,
  "downVoteCount": 0,
  "creationTs": 1736125524,
  "promoted": 0,
  "badges": [],
  "images": {
    "image700": {
      "width": 700,
      "height": 933,
      "url": "/assets/media/avyQ12q_image700.jpg"
    },
    "image460": {
      "width": 460,
      "height": 613,
      "url": "/assets/media/avyQ12q_image460.jpg"
    }
  },
  "commentsCount": 0,
  "tags": [
    {
      "key": "movie tv",
      "url": "/tag/movie-tv"
    },
    {
      "key": "rick and morty",
      "url": "/tag/rick-and-morty"
    }
  ],
  "interests": [
    "movies"
  ]
}