{
  "layout": "post",
  "id": "aW4GO43",
  "url": "/2024/12/31/aW4GO43.html",
  "post_url": "/2024/12/31/aW4GO43.html",
  "title": "Everything is a mod in skyrim huh",
  "description": "",
  "type": "Photo",
  "nsfw": 0,
  "upVoteCount": 5247,
  "downVoteCount": 165,
  "creationTs": 1735587126,
  "promoted": 0,
  "badges": [],
  "images": {
    "image700": {
      "width": 697,
      "height": 863,
      "url": "/assets/media/aW4GO43_image700.jpg"
    },
    "image460": {
      "width": 460,
      "height": 569,
      "url": "/assets/media/aW4GO43_image460.jpg"
    }
  },
  "commentsCount": 164,
  "tags": [
    {
      "key": "make 9gag great again",
      "url": "/tag/make-9gag-great-again"
    },
    {
      "key": "skyrim 2077",
      "url": "/tag/skyrim-2077"
    }
  ],
  "interests": [
    "games",
    "memes"
  ]
}